[{"metadata": {"doi": "10.1002/jlac.18631270102", "name": "Untersuchungen \u00fcber die Harns\u00e4uregruppe", "vertexIndex": 3559, "month": 1, "sqlIndex": 3561, "year": 1863, "day": 1}, "posX": 315.4303652968031, "posY": 5652.225537422604}, {"metadata": {"doi": "10.1002/jlac.18641300202", "name": "Mittheilungen aus dem organischen Laboratorium des Gewerbeinstitutes in Berlin: Untersuchungen \u00fcber die Harns\u00e4uregruppe", "vertexIndex": 3560, "month": 1, "sqlIndex": 3562, "year": 1864, "day": 1}, "posX": 320.4303652968031, "posY": 5673.092855217456}, {"metadata": {"doi": "10.1002/jlac.18822150302", "name": "Ueber Caffe\u00efn, Theobromin, Xanthin und Guanin", "vertexIndex": 3561, "month": 1, "sqlIndex": 3563, "year": 1882, "day": 1}, "posX": 410.4303652968031, "posY": 5645.006178771978}, {"metadata": {"doi": "10.1002/jlac.18832160112", "name": "Ueber das Delta-Lacton der normalen Caprons\u00e4ure", "vertexIndex": 3673, "month": 1, "sqlIndex": 3675, "year": 1883, "day": 1}, "posX": 415.4303652968031, "posY": 5651.175761415098}, {"metadata": {"doi": "10.1002/cber.18680010111", "name": "Ueber die dem Senf\u00f6l entsprechenden Isomeren der Schwefelcyanwasserstoff\u00e4ther", "vertexIndex": 3674, "month": 1, "sqlIndex": 3676, "year": 1868, "day": 1}, "posX": 340.4303652968031, "posY": 5763.155658009454}, {"metadata": {"doi": "10.1002/cber.187801102261", "name": "Ueber Acetopropions\u00e4ure und ihre Identit\u00e4t mit Levulins\u00e4ure", "vertexIndex": 3675, "month": 7, "sqlIndex": 3677, "year": 1878, "day": 1}, "posX": 392.9303652968031, "posY": 5757.280002617616}, {"metadata": {"doi": "10.1002/jlac.18751750113", "name": "Untersuchungen \u00fcber Kohlenhydrate. I. Ueber die bei Einwirkung von Schwefels\u00e4ure auf Zucker entstehende S\u00e4ure (Levulins\u00e4ure)", "vertexIndex": 3676, "month": 1, "sqlIndex": 3678, "year": 1875, "day": 1}, "posX": 375.4303652968031, "posY": 5870.312945404182}]