[{"metadata": {"doi": "10.1113/jphysiol.1901.sp000869", "name": "Observations on the physiological action of extracts of the supra-renal bodies", "vertexIndex": 1998, "month": 10, "sqlIndex": 2000, "year": 1901, "day": 16}, "posX": 509.3858447488583, "posY": 716.0405997293188}, {"metadata": {"doi": "10.1515/bchm2.1900.30.1-2.149", "name": "Ueber die fermentative Eiweissspaltung und Ammoniakbildung in der Leber.", "vertexIndex": 2143, "month": 1, "sqlIndex": 2145, "year": 1900, "day": 1}, "posX": 500.4303652968031, "posY": 628.1964326964222}, {"metadata": {"doi": "10.1007/bf02306738", "name": "Studien \u00fcber den Musc. dilatator pupillae samt Angabe von gemeinschaftlichen Kennzeichen einiger F\u00e4lle epithelialer Muskulatur", "vertexIndex": 2176, "month": 6, "sqlIndex": 2178, "year": 1900, "day": 1}, "posX": 502.5136986301368, "posY": 516.0472714742635}, {"metadata": {"doi": "10.1007/bf02956032", "name": "Ueber die Lymphkn\u00f6tchen des Darmes", "vertexIndex": 2181, "month": 12, "sqlIndex": 2183, "year": 1889, "day": 1}, "posX": 450.0136986301368, "posY": 521.6876534537897}, {"metadata": {"doi": "10.1113/jphysiol.1885.sp000199", "name": "Proceedings of the Physiological Society1885. No. III", "vertexIndex": 2572, "month": 7, "sqlIndex": 2574, "year": 1885, "day": 1}, "posX": 427.9303652968031, "posY": 727.4244624602984}, {"metadata": {"doi": "10.1016/s0140-6736(02)19594-8", "name": "THE GENERAL APPRECIATION OF VIBRATION AS A SENSE EXTRAORDINARY.", "vertexIndex": 2618, "month": 6, "sqlIndex": 2620, "year": 1890, "day": 1}, "posX": 452.5136986301368, "posY": 760.8454592102285}, {"metadata": {"doi": "10.1016/s0140-6736(01)54187-2", "name": "A CASE OF PERFORATING ULCERS OF BOTH FEET ASSOCIATED WITH DIABETES AND ATAXIC SYMPTOMS.", "vertexIndex": 2766, "month": 7, "sqlIndex": 2768, "year": 1887, "day": 1}, "posX": 437.9303652968031, "posY": 704.5438309129535}, {"metadata": {"doi": "10.1007/bf01966119", "name": "Ueber Cholesterin- und Kalkausscheidung mit der Galle", "vertexIndex": 3129, "month": 10, "sqlIndex": 3131, "year": 1891, "day": 1}, "posX": 459.1803652968031, "posY": 618.5424440342217}, {"metadata": {"doi": "10.1055/s-0029-1187111", "name": "Zur Methodik der F\u00e4kaluntersuchungen", "vertexIndex": 3146, "month": 10, "sqlIndex": 3148, "year": 1901, "day": 1}, "posX": 509.1803652968031, "posY": 527.2983966954499}, {"metadata": {"doi": "10.1002/cber.189002302181", "name": "Zur Kohlenstoffbestimmung organischer Substanzen auf nassem Wege", "vertexIndex": 3359, "month": 7, "sqlIndex": 3361, "year": 1890, "day": 1}, "posX": 452.9303652968031, "posY": 545.6612711329657}, {"metadata": {"doi": "10.1002/cber.18940270470", "name": "Allgemeine, Physikalische und Anorganische Chemie", "vertexIndex": 3360, "month": 1, "sqlIndex": 3362, "year": 1894, "day": 1}, "posX": 470.4303652968031, "posY": 537.6404674861593}, {"metadata": {"doi": "10.1002/cber.189402701122", "name": "Ueber die Bestimmung des Stickstoffes in Benzol-, Pyridin- und Chinolinderivaten nach der Kjeldahl'schen Methode", "vertexIndex": 3361, "month": 1, "sqlIndex": 3363, "year": 1894, "day": 1}, "posX": 470.4303652968031, "posY": 556.7028197144058}, {"metadata": {"doi": "10.1002/jlac.18922700302", "name": "Ueber das zweiwerthige Kohlenstoffatom", "vertexIndex": 3362, "month": 1, "sqlIndex": 3364, "year": 1892, "day": 1}, "posX": 460.4303652968031, "posY": 528.1653992140332}, {"metadata": {"doi": "10.1002/cber.18900230121", "name": "Ueber die Alkylirung der S\u00e4ureamide", "vertexIndex": 3378, "month": 1, "sqlIndex": 3380, "year": 1890, "day": 1}, "posX": 450.4303652968031, "posY": 520.6456882036008}, {"metadata": {"doi": "10.1002/cber.18900230216", "name": "Zur Kenntniss der Oxanils\u00e4ure", "vertexIndex": 3379, "month": 7, "sqlIndex": 3381, "year": 1890, "day": 1}, "posX": 452.9303652968031, "posY": 517.601313435147}, {"metadata": {"doi": "10.1002/cber.188902201159", "name": "Ueber das dritte Benzildioxim", "vertexIndex": 3384, "month": 1, "sqlIndex": 3386, "year": 1889, "day": 1}, "posX": 445.4303652968031, "posY": 542.7053378756582}, {"metadata": {"doi": "10.1002/cber.189102401212", "name": "Ueber die Monoxime der Bernsteins\u00e4ure", "vertexIndex": 3385, "month": 1, "sqlIndex": 3387, "year": 1891, "day": 1}, "posX": 455.4303652968031, "posY": 551.3377079081487}, {"metadata": {"doi": "10.1002/cber.189102401213", "name": "Ueber die Dioximidobernsteins\u00e4uren (Dioxime der Dioxyweins\u00e4ure)", "vertexIndex": 3386, "month": 1, "sqlIndex": 3388, "year": 1891, "day": 1}, "posX": 455.4303652968031, "posY": 548.4989724834822}, {"metadata": {"doi": "10.1002/jlac.18882490102", "name": "Untersuchungen \u00fcber Azole. Allgemeine Bemerkungen \u00fcber Azole", "vertexIndex": 3387, "month": 1, "sqlIndex": 3389, "year": 1888, "day": 1}, "posX": 440.4303652968031, "posY": 588.2507277359365}, {"metadata": {"doi": "10.1002/cber.18870200199", "name": "Ueber \u03b2-Broml\u00e4vulins\u00e4ure", "vertexIndex": 3390, "month": 1, "sqlIndex": 3392, "year": 1887, "day": 1}, "posX": 435.4303652968031, "posY": 597.4307560718802}, {"metadata": {"doi": "10.1002/cber.18880210277", "name": "Ueber die Natur der Tetrins\u00e4ure und ihrer Homologen", "vertexIndex": 3405, "month": 7, "sqlIndex": 3407, "year": 1888, "day": 1}, "posX": 442.9303652968031, "posY": 581.6953006583377}, {"metadata": {"doi": "10.1002/cber.188702002113", "name": "Zur Kenntniss der Isonitrosovalerians\u00e4ure und des \u03b3-Valerooximidolactons", "vertexIndex": 3406, "month": 7, "sqlIndex": 3408, "year": 1887, "day": 1}, "posX": 437.9303652968031, "posY": 618.339058389243}, {"metadata": {"doi": "10.1002/cber.188401702103", "name": "Zur Kenntniss der Orthonitrosonaphtole", "vertexIndex": 3407, "month": 7, "sqlIndex": 3409, "year": 1884, "day": 1}, "posX": 422.9303652968031, "posY": 586.962195873632}, {"metadata": {"doi": "10.1002/cber.18840170130", "name": "Ueber die Einwirkung von Hydroxylamin auf Nitrile", "vertexIndex": 3408, "month": 1, "sqlIndex": 3410, "year": 1884, "day": 1}, "posX": 420.4303652968031, "posY": 608.7691222259027}, {"metadata": {"doi": "10.1002/cber.188902202121", "name": "Neuere Beobachtungen \u00fcber Amidoxime und Azoxime", "vertexIndex": 3409, "month": 7, "sqlIndex": 3411, "year": 1889, "day": 1}, "posX": 447.9303652968031, "posY": 587.014486147848}, {"metadata": {"doi": "10.1002/cber.188702002213", "name": "Ueber gemischte S\u00e4ureanhydride", "vertexIndex": 3410, "month": 7, "sqlIndex": 3412, "year": 1887, "day": 1}, "posX": 437.9303652968031, "posY": 578.7915504179538}, {"metadata": {"doi": "10.1002/cber.188702001115", "name": "Zur Kenntniss der Acetoxime", "vertexIndex": 3415, "month": 1, "sqlIndex": 3417, "year": 1887, "day": 1}, "posX": 435.4303652968031, "posY": 618.304516322938}, {"metadata": {"doi": "10.1002/prac.18660990102", "name": "Ueber Glutamins\u00e4ure", "vertexIndex": 3416, "month": 1, "sqlIndex": 3418, "year": 1866, "day": 1}, "posX": 330.4303652968031, "posY": 550.3336873389723}, {"metadata": {"doi": "10.1002/jlac.18651330109", "name": "Ueber die von den Cyanverbindungen der Oxyradicale zwei\u2013 und dreiatomiger Alkohole ableitbaren S\u00e4uren", "vertexIndex": 3417, "month": 1, "sqlIndex": 3419, "year": 1865, "day": 1}, "posX": 325.4303652968031, "posY": 552.8724101879741}, {"metadata": {"doi": "10.1002/cber.18770100127", "name": "R. Gnehm, aus Z\u00fcrich, Januar 1877", "vertexIndex": 3418, "month": 1, "sqlIndex": 3420, "year": 1877, "day": 1}, "posX": 385.4303652968031, "posY": 619.8144761511749}, {"metadata": {"doi": "10.1002/cber.18840170235", "name": "Untersuchungen \u00fcber die Glutamins\u00e4ure", "vertexIndex": 3419, "month": 7, "sqlIndex": 3421, "year": 1884, "day": 1}, "posX": 422.9303652968031, "posY": 608.000466749433}, {"metadata": {"doi": "10.1002/cber.189202501162", "name": "Ueber die Constitution des Acetessig\u00e4thers und des sogenannten Formylessig\u00e4thers", "vertexIndex": 3420, "month": 1, "sqlIndex": 3422, "year": 1892, "day": 1}, "posX": 460.4303652968031, "posY": 601.0864553207484}, {"metadata": {"doi": "10.1002/jlac.18822140104", "name": "14. Methenyltricarbons\u00e4ureester und Acetmalons\u00e4ureester", "vertexIndex": 3460, "month": 1, "sqlIndex": 3462, "year": 1882, "day": 1}, "posX": 410.4303652968031, "posY": 520.9104571871782}, {"metadata": {"doi": "10.1002/cber.188702001293", "name": "Ueber Spaltungen des Acetmalons\u00e4ure\u00e4thers und seiner Homologen", "vertexIndex": 3461, "month": 1, "sqlIndex": 3463, "year": 1887, "day": 1}, "posX": 435.4303652968031, "posY": 529.515795700585}, {"metadata": {"doi": "10.1002/cber.18740070284", "name": "VII. Synthese des Triphenylmethans und des Methylphenyl-Diphenylmethans", "vertexIndex": 3486, "month": 7, "sqlIndex": 3488, "year": 1874, "day": 1}, "posX": 372.9303652968031, "posY": 576.2370649144216}, {"metadata": {"doi": "10.1002/jlac.18842220302", "name": "Synthesen mittelst Malons\u00e4ureester. Dicarboxylglutacons\u00e4ureester und dessen Derivate", "vertexIndex": 3514, "month": 1, "sqlIndex": 3516, "year": 1884, "day": 1}, "posX": 420.4303652968031, "posY": 689.3896331086105}, {"metadata": {"doi": "10.1002/cber.187400701288", "name": "Einwirkung des Chloroforms auf Natriumessig\u00e4ther", "vertexIndex": 3515, "month": 1, "sqlIndex": 3517, "year": 1874, "day": 1}, "posX": 370.4303652968031, "posY": 562.5649786166349}, {"metadata": {"doi": "10.1002/cber.187500801290", "name": "Die Oxyuvitins\u00e4ure und ihr Kresol", "vertexIndex": 3516, "month": 1, "sqlIndex": 3518, "year": 1875, "day": 1}, "posX": 375.4303652968031, "posY": 544.197952609967}, {"metadata": {"doi": "10.1002/cber.18830160189", "name": "Ueber eine neue mit der Itacons\u00e4ure isomere unges\u00e4ttigte S\u00e4ure", "vertexIndex": 3517, "month": 1, "sqlIndex": 3519, "year": 1883, "day": 1}, "posX": 415.4303652968031, "posY": 575.8073446792121}, {"metadata": {"doi": "10.1002/jlac.18832160106", "name": "Ueber eine eigenth\u00fcmliche Zersetzung der substituirten Acetylessig\u00e4ther", "vertexIndex": 3518, "month": 1, "sqlIndex": 3520, "year": 1883, "day": 1}, "posX": 415.4303652968031, "posY": 578.7330167913409}, {"metadata": {"doi": "10.1002/jlac.18842220102", "name": "Die Condensationsproducte des Acetessig\u00e4thers", "vertexIndex": 3519, "month": 1, "sqlIndex": 3521, "year": 1884, "day": 1}, "posX": 420.4303652968031, "posY": 670.3791327250359}, {"metadata": {"doi": "10.1002/cber.188301601167", "name": "Condensationsprodukte des Acetessig\u00e4thers", "vertexIndex": 3520, "month": 1, "sqlIndex": 3522, "year": 1883, "day": 1}, "posX": 415.4303652968031, "posY": 728.6994945505362}, {"metadata": {"doi": "10.1002/cber.188201501124", "name": "Die Condensation des Acetons", "vertexIndex": 3521, "month": 1, "sqlIndex": 3523, "year": 1882, "day": 1}, "posX": 410.4303652968031, "posY": 710.0267355929656}, {"metadata": {"doi": "10.1002/cber.189002302265", "name": "Sitzung vom 10. November 1890", "vertexIndex": 3522, "month": 7, "sqlIndex": 3524, "year": 1890, "day": 1}, "posX": 452.9303652968031, "posY": 739.4592715677901}, {"metadata": {"doi": "10.1002/cber.187701001198", "name": "Die Einwirkung des Schwefelkohlenstoffs auf Acetessig\u00e4ther", "vertexIndex": 3535, "month": 1, "sqlIndex": 3537, "year": 1877, "day": 1}, "posX": 385.4303652968031, "posY": 513.1818646298676}, {"metadata": {"doi": "10.1002/cber.18800130186", "name": "Ueber Phenylmilchs\u00e4uren", "vertexIndex": 3536, "month": 1, "sqlIndex": 3538, "year": 1880, "day": 1}, "posX": 400.4303652968031, "posY": 527.3084173083055}, {"metadata": {"doi": "10.1002/cber.18790120288", "name": "Erregung des Sauerstoffs durch nascirenden Wasserstoff", "vertexIndex": 3572, "month": 7, "sqlIndex": 3574, "year": 1879, "day": 1}, "posX": 397.9303652968031, "posY": 530.2496579094387}, {"metadata": {"doi": "10.1002/cber.18810140139", "name": "Ueber eine Dioxyadipins\u00e4ure", "vertexIndex": 3573, "month": 1, "sqlIndex": 3575, "year": 1881, "day": 1}, "posX": 405.4303652968031, "posY": 513.2256067429325}, {"metadata": {"doi": "10.1002/cber.188001302268", "name": "Ueber Oxydation des Di- und Trinitrobenzols", "vertexIndex": 3574, "month": 7, "sqlIndex": 3576, "year": 1880, "day": 1}, "posX": 402.9303652968031, "posY": 513.0640044271769}, {"metadata": {"doi": "10.1002/jlac.18731670112", "name": "Ueber isomere Dinitrophenole", "vertexIndex": 3575, "month": 1, "sqlIndex": 3577, "year": 1873, "day": 1}, "posX": 365.4303652968031, "posY": 535.6680406143338}, {"metadata": {"doi": "10.1002/jlac.18691490308", "name": "Ueber das Propylbenzol und Propyltoluol", "vertexIndex": 3576, "month": 1, "sqlIndex": 3578, "year": 1869, "day": 1}, "posX": 345.4303652968031, "posY": 531.112338321316}, {"metadata": {"doi": "10.1002/cber.18780110204", "name": "Oxydation der Cumins\u00e4ure durch \u00fcbermangansaures Kalium", "vertexIndex": 3577, "month": 7, "sqlIndex": 3579, "year": 1878, "day": 1}, "posX": 392.9303652968031, "posY": 512.1892718179284}, {"metadata": {"doi": "10.1002/cber.188101401233", "name": "Oxydation der Isocymolsulfos\u00e4ure durch Kaliumpermanganat", "vertexIndex": 3580, "month": 1, "sqlIndex": 3582, "year": 1881, "day": 1}, "posX": 405.4303652968031, "posY": 549.8444107423245}, {"metadata": {"doi": "10.1002/cber.188101402177", "name": "Notiz \u00fcber Darstellung und Eigenschaften des Benzylalkohols", "vertexIndex": 3581, "month": 7, "sqlIndex": 3583, "year": 1881, "day": 1}, "posX": 407.9303652968031, "posY": 513.8922440326772}, {"metadata": {"doi": "10.1002/cber.187801101279", "name": "Ueber die Isooxycumins\u00e4ure aus Carvacrol", "vertexIndex": 3582, "month": 1, "sqlIndex": 3584, "year": 1878, "day": 1}, "posX": 390.4303652968031, "posY": 512.5925624757048}, {"metadata": {"doi": "10.1002/cber.187500802109", "name": "Synthese des Cumols", "vertexIndex": 3585, "month": 7, "sqlIndex": 3587, "year": 1875, "day": 1}, "posX": 377.9303652968031, "posY": 533.4875782215614}, {"metadata": {"doi": "10.1002/jlac.18832200102", "name": "Untersuchungen \u00fcber Hydroxylirung durch directe Oxydation", "vertexIndex": 3586, "month": 1, "sqlIndex": 3588, "year": 1883, "day": 1}, "posX": 415.4303652968031, "posY": 541.1006798409273}, {"metadata": {"doi": "10.1002/cber.18960290177", "name": "Ueber Reduction unges\u00e4ttigter Ketone", "vertexIndex": 3645, "month": 1, "sqlIndex": 3647, "year": 1896, "day": 1}, "posX": 480.4303652968031, "posY": 578.3421125930271}, {"metadata": {"doi": "10.1002/jlac.18942810104", "name": "1,5-Diketone", "vertexIndex": 3646, "month": 1, "sqlIndex": 3648, "year": 1894, "day": 1}, "posX": 470.4303652968031, "posY": 756.7469061342878}, {"metadata": {"doi": "10.1002/jlac.18842260302", "name": "Ueber die Constitution der Camphorons\u00e4ure", "vertexIndex": 3653, "month": 1, "sqlIndex": 3655, "year": 1884, "day": 1}, "posX": 420.4303652968031, "posY": 760.1618031675516}, {"metadata": {"doi": "10.1002/cber.188601902105", "name": "Ueber die Einwirkung von Ammoniumformiat auf Benzaldehyd und Benzophenon", "vertexIndex": 3658, "month": 7, "sqlIndex": 3660, "year": 1886, "day": 1}, "posX": 432.9303652968031, "posY": 753.7798319590912}, {"metadata": {"doi": "10.1002/jlac.18892530107", "name": "Ueber das Anhydrid der Phenylhydrazonl\u00e4vulins\u00e4ure", "vertexIndex": 3667, "month": 1, "sqlIndex": 3669, "year": 1889, "day": 1}, "posX": 445.4303652968031, "posY": 713.9461018789849}, {"metadata": {"doi": "10.1002/cber.189102402273", "name": "Ueber die Isoxazole", "vertexIndex": 3668, "month": 7, "sqlIndex": 3670, "year": 1891, "day": 1}, "posX": 457.9303652968031, "posY": 698.6761602301019}, {"metadata": {"doi": "10.1002/jlac.18862360105", "name": "Synthetische Versuche mit dem Acetessigester", "vertexIndex": 3680, "month": 1, "sqlIndex": 3682, "year": 1886, "day": 1}, "posX": 430.4303652968031, "posY": 695.1977135324363}, {"metadata": {"doi": "10.1002/cber.18780110178", "name": "Ueber Nitrosoverbindungen der Fettreihe", "vertexIndex": 3690, "month": 1, "sqlIndex": 3692, "year": 1878, "day": 1}, "posX": 390.4303652968031, "posY": 687.2598278699282}, {"metadata": {"doi": "10.1002/jlac.18852270304", "name": "V. Ueber die Einwirkung von Schwefels\u00e4ure auf die beiden Phenylcrotons\u00e4uren", "vertexIndex": 3691, "month": 1, "sqlIndex": 3693, "year": 1885, "day": 1}, "posX": 425.4303652968031, "posY": 700.2007575776439}, {"metadata": {"doi": "10.1002/cber.187801102282", "name": "Verfahren zur Bestimmung der Dampfdichte oberhalb 440\u00b0 siedender K\u00f6rper, sowie solcher Substanzen, welche Quecksilber oder Wood'sches Metall angreifen", "vertexIndex": 3692, "month": 7, "sqlIndex": 3694, "year": 1878, "day": 1}, "posX": 392.9303652968031, "posY": 671.4329238137776}, {"metadata": {"doi": "10.1002/cber.188702001110", "name": "Ueber die Abk\u00f6mmlinge des Camphoroxims", "vertexIndex": 3693, "month": 1, "sqlIndex": 3695, "year": 1887, "day": 1}, "posX": 435.4303652968031, "posY": 693.9437870019458}, {"metadata": {"doi": "10.1002/cber.18970300146", "name": "Ueber die Einwirkung von Hydroxylamin auf Phoron", "vertexIndex": 3694, "month": 1, "sqlIndex": 3696, "year": 1897, "day": 1}, "posX": 485.4303652968031, "posY": 767.962768796987}, {"metadata": {"doi": "10.1002/jlac.18942800105", "name": "Ueber die p - Methylendihydrobenzo\u00ebs\u00e4ure", "vertexIndex": 3695, "month": 1, "sqlIndex": 3697, "year": 1894, "day": 1}, "posX": 470.4303652968031, "posY": 561.7664990999397}, {"metadata": {"doi": "10.1002/jlac.18731660307", "name": "Ueber die Melliths\u00e4ure. Die Polycarbons\u00e4uren des Benzols", "vertexIndex": 3751, "month": 1, "sqlIndex": 3753, "year": 1873, "day": 1}, "posX": 365.4303652968031, "posY": 564.555901624093}, {"metadata": {"doi": "10.1002/cber.18710040195", "name": "Ueber Biuret und verwandte Verbindungen", "vertexIndex": 3752, "month": 1, "sqlIndex": 3754, "year": 1871, "day": 1}, "posX": 355.4303652968031, "posY": 587.354965681215}, {"metadata": {"doi": "10.1002/cber.18710040210", "name": "Ueber die Einwirkung der Jodwasserstoffs\u00e4ure auf Hydrophtals\u00e4ure", "vertexIndex": 3753, "month": 6, "sqlIndex": 3755, "year": 1871, "day": 1}, "posX": 357.5136986301368, "posY": 568.4538261677728}, {"metadata": {"doi": "10.1002/cber.188101401187", "name": "Ueber eine neue Bromirungsmethode organischer S\u00e4uren", "vertexIndex": 3766, "month": 1, "sqlIndex": 3768, "year": 1881, "day": 1}, "posX": 405.4303652968031, "posY": 543.355700646865}, {"metadata": {"doi": "10.1002/jlac.18812090207", "name": "Synthesen mittelst Malons\u00e4ureester. Ueber Aethyl- und Isobutylchlormalons\u00e4ureester, Aethyl- und Isobutyltartrons\u00e4ure, Aethyl- und Isobutylhydroxyessigs\u00e4ure", "vertexIndex": 3767, "month": 1, "sqlIndex": 3769, "year": 1881, "day": 1}, "posX": 405.4303652968031, "posY": 564.3594049583203}, {"metadata": {"doi": "10.1002/cber.187400701223", "name": "Ueber die Darstellung des Methyl\u00e4thers", "vertexIndex": 3871, "month": 1, "sqlIndex": 3873, "year": 1874, "day": 1}, "posX": 370.4303652968031, "posY": 620.3684051568846}, {"metadata": {"doi": "10.1002/jlac.18962910102", "name": "Ueber Dibiphenylen\u00e4then und Dibiphenyl\u00e4than", "vertexIndex": 3936, "month": 1, "sqlIndex": 3938, "year": 1896, "day": 1}, "posX": 480.4303652968031, "posY": 566.50023682382}, {"metadata": {"doi": "10.1002/cber.18860190291", "name": "Ueber eine eigenth\u00fcmliche Reaction der Malons\u00e4ure", "vertexIndex": 3937, "month": 7, "sqlIndex": 3939, "year": 1886, "day": 1}, "posX": 432.9303652968031, "posY": 543.535292506367}, {"metadata": {"doi": "10.1002/cber.190203502175", "name": "Synthesen in der Pyridinreihe (IV. Mittheilung). Ueber eine Erweiterung der Hantzsch'schen Dihydropyridinsynthese", "vertexIndex": 3993, "month": 4, "sqlIndex": 3995, "year": 1902, "day": 1}, "posX": 511.6803652968031, "posY": 546.9469963827853}, {"metadata": {"doi": "10.1002/jlac.18601150325", "name": "Ueber ein neues Methylenderivat", "vertexIndex": 4082, "month": 1, "sqlIndex": 4084, "year": 1860, "day": 1}, "posX": 300.4303652968031, "posY": 563.0272524513506}]